myanimelist/__init__.py
myanimelist/anime.py
myanimelist/anime_list.py
myanimelist/base.py
myanimelist/character.py
myanimelist/club.py
myanimelist/genre.py
myanimelist/manga.py
myanimelist/manga_list.py
myanimelist/media.py
myanimelist/media_list.py
myanimelist/myanimelist.py
myanimelist/person.py
myanimelist/producer.py
myanimelist/publication.py
myanimelist/session.py
myanimelist/tag.py
myanimelist/user.py
myanimelist/utilities.py
python3_mal-0.2.21.dist-info/LICENSE.txt
python3_mal-0.2.21.dist-info/METADATA
python3_mal-0.2.21.dist-info/WHEEL
python3_mal-0.2.21.dist-info/top_level.txt
python3_mal-0.2.21.dist-info/RECORD
