Metadata-Version: 2.1
Name: python3-mal
Version: 0.2.21
Summary: Provides programmatic access to MyAnimeList resources.
Home-page: https://github.com/pushrbx/python3-mal
Author: pushrbx
Author-email: contact@pushrbx.net
License: LICENSE.txt
Download-URL: https://github.com/pushrbx/python3-mal/archive/master.zip
Keywords: myanimelist,mal-api,mal python,myanimelist python,python3-mal,myanimelist api
Platform: UNKNOWN
Requires-Python: >=3.4, <4
Requires-Dist: urllib3 (<1.23,>=1.21.1)
Requires-Dist: requests (<=2.18.4)
Requires-Dist: pytz
Requires-Dist: lxml (==4.5.1)
Requires-Dist: cssselect
